aws_orbit_sdk/__init__.py
aws_orbit_sdk/common.py
aws_orbit_sdk/controller.py
aws_orbit_sdk/database.py
aws_orbit_sdk/emr.py
aws_orbit_sdk/glue_catalog.py
aws_orbit_sdk/json.py
aws_orbit_sdk/transformations.py
aws_orbit_sdk/magics/__init__.py
aws_orbit_sdk/magics/database.py
aws_orbit_sdk/magics/orbit.py
aws_orbit_sdk-1.4.0.dist-info/LICENSE
aws_orbit_sdk-1.4.0.dist-info/METADATA
aws_orbit_sdk-1.4.0.dist-info/NOTICE
aws_orbit_sdk-1.4.0.dist-info/VERSION
aws_orbit_sdk-1.4.0.dist-info/WHEEL
aws_orbit_sdk-1.4.0.dist-info/top_level.txt
aws_orbit_sdk-1.4.0.dist-info/RECORD
