Metadata-Version: 2.1
Name: aws-orbit-sdk
Version: 1.4.0
Summary: AWS Orbit Workbench SDK
Home-page: https://github.com/awslabs/aws-orbit-workbench
Author: AWS Professional Services
Author-email: aws-proserve-opensource@amazon.com
License: UNKNOWN
Project-URL: Org Site, https://aws.amazon.com/professional-services/
Keywords: aws,cdk
Platform: UNKNOWN
Classifier: Development Status :: 4 - Beta
Classifier: Intended Audience :: Developers
Classifier: Intended Audience :: Information Technology
Classifier: Intended Audience :: Science/Research
Classifier: License :: OSI Approved :: Apache Software License
Classifier: Programming Language :: JavaScript
Classifier: Programming Language :: Python :: 3 :: Only
Classifier: Programming Language :: Python :: 3.7
Classifier: Programming Language :: Python :: 3.8
Classifier: Topic :: Software Development :: Code Generators
Classifier: Topic :: Utilities
Classifier: Typing :: Typed
Requires-Python: >=3.7
Requires-Dist: boto3 (~=1.18.0)
Requires-Dist: pyyaml (~=5.4)
Requires-Dist: ipython (~=7.23.0)
Requires-Dist: pandas (<=1.2.0,>=1.1.0)
Requires-Dist: psycopg2-binary (~=2.8.4)
Requires-Dist: SQLAlchemy (<1.3.16,>=1.3.10)
Requires-Dist: sqlalchemy-redshift (~=0.7.5)
Requires-Dist: requests (<=2.26.0,>=2.24.0)
Requires-Dist: kubernetes (~=12.0.1)
Requires-Dist: python-slugify (~=4.0.1)
